n_factorial/__init__.py
n_factorial/factorial.py
simple_fact_py-0.1.1.dist-info/METADATA
simple_fact_py-0.1.1.dist-info/WHEEL
simple_fact_py-0.1.1.dist-info/top_level.txt
simple_fact_py-0.1.1.dist-info/RECORD
